{
  "/_not-found/page": "app/_not-found/page.js",
  "/page": "app/page.js",
  "/(dashboard)/campaigns/page": "app/(dashboard)/campaigns/page.js",
  "/(dashboard)/campaigns/[id]/page": "app/(dashboard)/campaigns/[id]/page.js",
  "/(dashboard)/analytics/page": "app/(dashboard)/analytics/page.js",
  "/(dashboard)/clips/page": "app/(dashboard)/clips/page.js",
  "/(dashboard)/command/page": "app/(dashboard)/command/page.js",
  "/(dashboard)/pages/page": "app/(dashboard)/pages/page.js",
  "/(dashboard)/health/page": "app/(dashboard)/health/page.js"
}